Week6/counter/ud_counter.v
module tff(input clk,input rstn,input t,output reg q);
always @ (negedge clk)begin
if(!rstn)
  q<=0;
else 
   if(t)
    q<=~q;
   else
    q<=q;
end
endmodule 


module ud_counter (input clk,
                input rstn,
                output reg [3:0] out);
wire [3:0] cnt;              
tff t0(.clk(clk),.rstn(rstn),.t(1'b1),.q(cnt[0]));
tff t1(.clk(cnt[0]),.rstn(rstn),.t(1'b1),.q(cnt[1]));
tff t2(.clk(cnt[1]),.rstn(rstn),.t(1'b1),.q(cnt[2]));
tff t3(.clk(cnt[2]),.rstn(rstn),.t(1'b1),.q(cnt[3]));               
always@*
begin
 out<=cnt;
end
endmodule

Week6/counter/tb_ud_counter.v
`timescale 1ns/1ps
module tb_counter();
reg clk,rstn;
wire [3:0]out;

ud_counter c0(clk,rstn,out);

always #5 clk=~clk;
initial
 begin
    $dumpfile("tb_counter.vcd");
    $dumpvars(0,tb_counter);
 end

initial begin
  clk<=0;
  rstn<=0;
  #20 rstn<=1;
  #150 rstn<=0;
  #50 rstn<=1;
  #200$finish;
end
endmodule

Week6/counter/tb_counter.vcd
$date
	Sat Apr  1 15:55:29 2023
$end
$version
	Icarus Verilog
$end
$timescale
	1ps
$end
$scope module tb_counter $end
$var wire 4 ! out [3:0] $end
$var reg 1 " clk $end
$var reg 1 # rstn $end
$scope module c0 $end
$var wire 1 " clk $end
$var wire 1 # rstn $end
$var wire 4 $ cnt [3:0] $end
$var reg 4 % out [3:0] $end
$scope module t0 $end
$var wire 1 " clk $end
$var wire 1 # rstn $end
$var wire 1 & t $end
$var reg 1 ' q $end
$upscope $end
$scope module t1 $end
$var wire 1 ( clk $end
$var wire 1 # rstn $end
$var wire 1 ) t $end
$var reg 1 * q $end
$upscope $end
$scope module t2 $end
$var wire 1 + clk $end
$var wire 1 # rstn $end
$var wire 1 , t $end
$var reg 1 - q $end
$upscope $end
$scope module t3 $end
$var wire 1 . clk $end
$var wire 1 # rstn $end
$var wire 1 / t $end
$var reg 1 0 q $end
$upscope $end
$upscope $end
$upscope $end
$enddefinitions $end
#0
$dumpvars
00
1/
0.
0-
1,
0+
0*
1)
0(
0'
1&
b0 %
b0 $
0#
0"
b0 !
$end
#5000
1"
#10000
0"
#15000
1"
#20000
1#
0"
#25000
1"
#30000
b1 !
b1 %
1(
b1 $
1'
0"
#35000
1"
#40000
1+
1*
b10 !
b10 %
0(
b10 $
0'
0"
#45000
1"
#50000
b11 !
b11 %
1(
b11 $
1'
0"
#55000
1"
#60000
1.
1-
0+
0*
b100 !
b100 %
0(
b100 $
0'
0"
#65000
1"
#70000
b101 !
b101 %
1(
b101 $
1'
0"
#75000
1"
#80000
1+
1*
b110 !
b110 %
0(
b110 $
0'
0"
#85000
1"
#90000
b111 !
b111 %
1(
b111 $
1'
0"
#95000
1"
#100000
10
0.
0-
0+
0*
b1000 !
b1000 %
0(
b1000 $
0'
0"
#105000
1"
#110000
b1001 !
b1001 %
1(
b1001 $
1'
0"
#115000
1"
#120000
1+
1*
b1010 !
b1010 %
0(
b1010 $
0'
0"
#125000
1"
#130000
b1011 !
b1011 %
1(
b1011 $
1'
0"
#135000
1"
#140000
1.
1-
0+
0*
b1100 !
b1100 %
0(
b1100 $
0'
0"
#145000
1"
#150000
b1101 !
b1101 %
1(
b1101 $
1'
0"
#155000
1"
#160000
1+
1*
b1110 !
b1110 %
0(
b1110 $
0'
0"
#165000
1"
#170000
b1111 !
b1111 %
1(
b1111 $
1'
0#
0"
#175000
1"
#180000
00
0.
0-
0+
0*
b0 !
b0 %
0(
b0 $
0'
0"
#185000
1"
#190000
0"
#195000
1"
#200000
0"
#205000
1"
#210000
0"
#215000
1"
#220000
1#
0"
#225000
1"
#230000
b1 !
b1 %
1(
b1 $
1'
0"
#235000
1"
#240000
1+
1*
b10 !
b10 %
0(
b10 $
0'
0"
#245000
1"
#250000
b11 !
b11 %
1(
b11 $
1'
0"
#255000
1"
#260000
1.
1-
0+
0*
b100 !
b100 %
0(
b100 $
0'
0"
#265000
1"
#270000
b101 !
b101 %
1(
b101 $
1'
0"
#275000
1"
#280000
1+
1*
b110 !
b110 %
0(
b110 $
0'
0"
#285000
1"
#290000
b111 !
b111 %
1(
b111 $
1'
0"
#295000
1"
#300000
10
0.
0-
0+
0*
b1000 !
b1000 %
0(
b1000 $
0'
0"
#305000
1"
#310000
b1001 !
b1001 %
1(
b1001 $
1'
0"
#315000
1"
#320000
1+
1*
b1010 !
b1010 %
0(
b1010 $
0'
0"
#325000
1"
#330000
b1011 !
b1011 %
1(
b1011 $
1'
0"
#335000
1"
#340000
1.
1-
0+
0*
b1100 !
b1100 %
0(
b1100 $
0'
0"
#345000
1"
#350000
b1101 !
b1101 %
1(
b1101 $
1'
0"
#355000
1"
#360000
1+
1*
b1110 !
b1110 %
0(
b1110 $
0'
0"
#365000
1"
#370000
b1111 !
b1111 %
1(
b1111 $
1'
0"
#375000
1"
#380000
00
0.
0-
0+
0*
b0 !
b0 %
0(
b0 $
0'
0"
#385000
1"
#390000
b1 !
b1 %
1(
b1 $
1'
0"
#395000
1"
#400000
1+
1*
b10 !
b10 %
0(
b10 $
0'
0"
#405000
1"
#410000
b11 !
b11 %
1(
b11 $
1'
0"
#415000
1"
#420000
1.
1-
0+
0*
b100 !
b100 %
0(
b100 $
0'
0"
